{
  "id": "wod-fight-module",
  "title": "WoD 20th Combat Tracker",
  "description": "Adds a two-phase combat system (Declaration/Execution) for World of Darkness 20th Anniversary Edition.",
  "version": "1.0.0",
  "compatibility": {
    "minimum": 13,
    "verified": 13
  },
  "scripts": [
    "scripts/main.js"
  ],
  "styles": [
    "styles/module.css"
  ],
  "languages": [
    {
      "lang": "en",
      "name": "English",
      "path": "languages/en.json"
    },
    {
      "lang": "ru",
      "name": "Русский",
      "path": "languages/ru.json"
    }
  ],
  "authors": [
    {
      "name": "Antigravity"
    }
  ],
  "manifest": "https://<GITHUB_TOKEN>@raw.githubusercontent.com/<YOUR_GITHUB_NAME>/wod-fight-module/main/module.json",
  "download": "https://<GITHUB_TOKEN>@github.com/<YOUR_GITHUB_NAME>/wod-fight-module/archive/refs/heads/main.zip"
}
